{
  "boba_mainnet": {
    "tokenAddress": "0x0000000000000000000000000000000000000000",
    "paymentToken": "0x5DE1677344D3Cb0D7D465c10b72A8f60699C062d",
    "totalTokens": "10500000",
    "tokenPriceInPT": "0.1",
    "saleOwner": "0x80A438DE3812421b144E886fDf53f23028420600",
    "registrationStartAt": 1639062000,
    "registrationLength": 226800,
    "delayBetweenRegistrationAndSale": 86400,
    "validatorRoundLength": 32400,
    "stakingRoundLength": 54000,
    "TGE": 1639742400,
    "portionVestingPrecision": 10000,
    "maxVestingTimeShift": 2592000,
    "unlockingTimes": [
      1639742400, 1642420800, 1645099200, 1647518400, 1650196800, 1652788800,
      1655467200, 1658059200, 1660737600, 1663416000, 1666008000, 1668686400,
      1671278400
    ],
    "portionPercents": [
      1000, 750, 750, 750, 750, 750, 750, 750, 750, 750, 750, 750, 750
    ],
    "maxParticipation": "100000"
  },
  "boba_rinkeby": {
    "tokenAddress": "0xEB8fF00096dFE654F1ED6d8Eb5e4a3D47769c1d0",
    "paymentToken": "0x9d0364c866A73e34649869525CD7576080259A42",
    "PTDecimal": 6,
    "totalTokens": "1000000",
    "tokenPriceInPT": "0.7655",
    "saleOwner": "0x01cc678Eede87483eCB18d487c3d078a2bc5e4b4",
    "registrationStartAt": 1649839504,
    "registrationLength": 18000,
    "delayBetweenRegistrationAndSale": 1,
    "saleRoundLength": 1800,
    "TGE": 1649859305,
    "portionVestingPrecision": 1000,
    "maxVestingTimeShift": 2592000,
    "unlockingTimes": [1649859305],
    "portionPercents": [1000],
    "maxParticipation": "100000"
  },
  "rinkeby": {
    "tokenAddress": "0xB8CA021dd54648f6721549a872323777AF00d0fF",
    "paymentToken": "0xD9BA894E0097f8cC2BBc9D24D308b98e36dc6D02",
    "totalTokens": "10000000",
    "tokenPriceInPT": "0.04",
    "saleOwner": "0xe6CEf4eE7c2757dF130a63e85a3849Ec56E812ef",
    "registrationStartAt": 1641719319,
    "registrationLength": 600,
    "delayBetweenRegistrationAndSale": 100,
    "saleRoundLength": 3600,
    "TGE": 1649168201,
    "portionVestingPrecision": 1000,
    "maxVestingTimeShift": 2592000,
    "unlockingTimes": [1649168201],
    "portionPercents": [1000],
    "maxParticipation": "100000"
  },
  "bsc_testnet": {
    "tokenAddress": "0x8AF8cF2B192280EFdd7Ef87AAa50EEB9FD59401a",
    "paymentToken": "0x7ef95a0FEE0Dd31b22626fA2e10Ee6A223F8a684",
    "PTDecimal": 18,
    "totalTokens": "1000000",
    "tokenPriceInPT": "0.04",
    "saleOwner": "0xe6CEf4eE7c2757dF130a63e85a3849Ec56E812ef",
    "registrationStartAt": 1649165734,
    "registrationLength": 600,
    "delayBetweenRegistrationAndSale": 10,
    "saleRoundLength": 600,
    "TGE": 1649166944,
    "portionVestingPrecision": 1000,
    "maxVestingTimeShift": 2592000,
    "unlockingTimes": [1649166944],
    "portionPercents": [1000],
    "maxParticipation": "100000"
  },
  "local": {
    "tokenAddress": "0xeA9172ad135cC8757400d7aB37B47132635c2732",
    "paymentToken": "0x55d398326f99059fF775485246999027B3197955",
    "totalTokens": "10000000",
    "tokenPriceInPT": "0.04",
    "saleOwner": "0x8365F0d042d7F226794308Ed7181DD2Bf4711f81",
    "registrationStartAt": 1641544500,
    "registrationLength": 600,
    "delayBetweenRegistrationAndSale": 600,
    "saleRoundLength": 86400,
    "TGE": 1641630616,
    "portionVestingPrecision": 1000,
    "maxVestingTimeShift": 2592000,
    "unlockingTimes": [1641630616],
    "portionPercents": [1000],
    "maxParticipation": "1000000"
  }
}
